odoo8_addon_website_crm_address-8.0.1.0.0.99.dev13-py2.7-nspkg.pth
odoo8_addon_website_crm_address-8.0.1.0.0.99.dev13.dist-info/METADATA
odoo8_addon_website_crm_address-8.0.1.0.0.99.dev13.dist-info/RECORD
odoo8_addon_website_crm_address-8.0.1.0.0.99.dev13.dist-info/WHEEL
odoo8_addon_website_crm_address-8.0.1.0.0.99.dev13.dist-info/namespace_packages.txt
odoo8_addon_website_crm_address-8.0.1.0.0.99.dev13.dist-info/top_level.txt
odoo_addons/website_crm_address/README.rst
odoo_addons/website_crm_address/__init__.py
odoo_addons/website_crm_address/__openerp__.py
odoo_addons/website_crm_address/controllers/__init__.py
odoo_addons/website_crm_address/controllers/main.py
odoo_addons/website_crm_address/i18n/ca.po
odoo_addons/website_crm_address/i18n/de.po
odoo_addons/website_crm_address/i18n/el_GR.po
odoo_addons/website_crm_address/i18n/es.po
odoo_addons/website_crm_address/i18n/eu.po
odoo_addons/website_crm_address/i18n/fi.po
odoo_addons/website_crm_address/i18n/fr.po
odoo_addons/website_crm_address/i18n/it.po
odoo_addons/website_crm_address/i18n/nl.po
odoo_addons/website_crm_address/i18n/nl_NL.po
odoo_addons/website_crm_address/i18n/pt.po
odoo_addons/website_crm_address/i18n/pt_BR.po
odoo_addons/website_crm_address/i18n/ro.po
odoo_addons/website_crm_address/i18n/ru.po
odoo_addons/website_crm_address/i18n/sl.po
odoo_addons/website_crm_address/i18n/tr.po
odoo_addons/website_crm_address/i18n/website_crm_address.pot
odoo_addons/website_crm_address/static/description/icon.png
odoo_addons/website_crm_address/views/contactus_form.xml
